one_api_cli/__init__.py
one_api_cli/account.py
one_api_cli/auth.py
one_api_cli/channel.py
one_api_cli-1.0.0.dist-info/LICENSE
one_api_cli-1.0.0.dist-info/METADATA
one_api_cli-1.0.0.dist-info/WHEEL
one_api_cli-1.0.0.dist-info/top_level.txt
one_api_cli-1.0.0.dist-info/RECORD
