Metadata-Version: 2.1
Name: one-api-cli
Version: 1.0.0
Summary: A CLI tool for the One API project.
Author-email: Rex Wang <1073853456@qq.com>
License: MIT License
Project-URL: Bug Tracker, https://github.com/rexwzh/one-api-cli/issues
Keywords: oneapi,cli,tool
Classifier: Programming Language :: Python :: 3
Classifier: License :: OSI Approved :: MIT License
Classifier: Operating System :: MacOS
Classifier: Operating System :: POSIX :: Linux
Requires-Python: <3.12,>=3.9
License-File: LICENSE
Requires-Dist: loguru
Requires-Dist: click
Requires-Dist: requests
Provides-Extra: all
Requires-Dist: ipython ; extra == 'all'
Requires-Dist: notebook ; extra == 'all'
Requires-Dist: pytest ; extra == 'all'
Requires-Dist: sphinx ; extra == 'all'
Requires-Dist: sphinx-rtd-theme ; extra == 'all'
Requires-Dist: mypy ; extra == 'all'
Provides-Extra: dev
Requires-Dist: ipython ; extra == 'dev'
Requires-Dist: notebook ; extra == 'dev'
Provides-Extra: docs
Requires-Dist: sphinx ; extra == 'docs'
Requires-Dist: sphinx-rtd-theme ; extra == 'docs'
Provides-Extra: lint
Requires-Dist: mypy ; extra == 'lint'
Provides-Extra: test
Requires-Dist: pytest ; extra == 'test'
